{"crs": {"type": "name", "properties": {"name": "urn:ogc:def:crs:OGC:1.3:CRS84"}}, "type": "FeatureCollection", "features": [{"geometry": {"type": "Point", "coordinates": [31.2167252, -85.3630676]}, "type": "Feature", "properties": {"Secondary ID": "SOUTHEAST ALABAMA MEDICAL CENTER", "Primary ID": 10001}}, {"geometry": {"type": "Point", "coordinates": [33.7749644, -85.8944399]}, "type": "Feature", "properties": {"Secondary ID": "MARSHALL MEDICAL CENTER SOUTH", "Primary ID": 10005}}, {"geometry": {"type": "Point", "coordinates": [31.5270585, -87.3462183]}, "type": "Feature", "properties": {"Secondary ID": "ELIZA COFFEE MEMORIAL HOSPITAL", "Primary ID": 10006}}, {"geometry": {"type": "Point", "coordinates": [31.316182, -85.856209]}, "type": "Feature", "properties": {"Secondary ID": "MIZELL MEMORIAL HOSPITAL", "Primary ID": 10007}}, {"geometry": {"type": "Point", "coordinates": [34.4573532, -88.1418714]}, "type": "Feature", "properties": {"Secondary ID": "CRENSHAW COMMUNITY HOSPITAL", "Primary ID": 10008}}, {"geometry": {"type": "Point", "coordinates": [34.446233, -86.93656]}, "type": "Feature", "properties": {"Secondary ID": "HARTSELLE MEDICAL CENTER", "Primary ID": 10009}}, {"geometry": {"type": "Point", "coordinates": [34.366053, -86.421267]}, "type": "Feature", "properties": {"Secondary ID": "MARSHALL MEDICAL CENTER NORTH", "Primary ID": 10010}}, {"geometry": {"type": "Point", "coordinates": [33.596457, -86.6676502]}, "type": "Feature", "properties": {"Secondary ID": "ST VINCENTS EAST", "Primary ID": 10011}}, {"geometry": {"type": "Point", "coordinates": [32.9236651, -86.7206433]}, "type": "Feature", "properties": {"Secondary ID": "DEKALB REGIONAL MEDICAL CENTER", "Primary ID": 10012}}, {"geometry": {"type": "Point", "coordinates": [30.9107827, -88.0351964]}, "type": "Feature", "properties": {"Secondary ID": "SOUTHWEST ALABAMA MEDICAL CENTER", "Primary ID": 10015}}]}